{
  "no": "429",
  "idx": 429,
  "name": {
    "jpn": "ムウマージ",
    "chs": "梦妖魔"
  },
  "slug": "mismagius",
  "available": [
    {
      "generation": "IV",
      "games": [
        "d",
        "p",
        "pt",
        "hg",
        "ss"
      ],
      "available": [
        "T",
        "E",
        "T",
        "E",
        "E"
      ]
    },
    {
      "generation": "V",
      "games": [
        "b",
        "w",
        "b2",
        "w2"
      ],
      "available": [
        "DWE",
        "C",
        "DWE",
        "DWE"
      ]
    },
    {
      "generation": "VI",
      "games": [
        "x",
        "y",
        "or",
        "as"
      ],
      "available": [
        "T",
        "T",
        "E",
        "E"
      ]
    },
    {
      "generation": "VII",
      "games": [
        "s",
        "m",
        "us",
        "um"
      ],
      "available": [
        "C",
        "C",
        "E",
        "E"
      ]
    },
    {
      "generation": "VIII",
      "games": [
        "bd",
        "sp",
        "la"
      ],
      "available": [
        "T",
        "E",
        "C"
      ]
    }
  ]
}