{
  "no": "710",
  "idx": 710,
  "name": {
    "jpn": "バケッチャ",
    "chs": "南瓜精"
  },
  "slug": "pumpkaboo",
  "available": [
    {
      "generation": "VI",
      "games": [
        "x",
        "y",
        "or",
        "as"
      ],
      "available": [
        "C",
        "C",
        "Ev",
        "Ev"
      ]
    },
    {
      "generation": "VII",
      "games": [
        "s",
        "m",
        "us",
        "um"
      ],
      "available": [
        "T",
        "T",
        "T",
        "T"
      ]
    },
    {
      "generation": "VIII",
      "games": [
        "sw",
        "sh"
      ],
      "available": [
        "C",
        "C"
      ]
    }
  ]
}